LICENSE
README.md
setup.py
src/imgen/__init__.py
src/imgen/image.py
src/pyimgmod.egg-info/PKG-INFO
src/pyimgmod.egg-info/SOURCES.txt
src/pyimgmod.egg-info/dependency_links.txt
src/pyimgmod.egg-info/requires.txt
src/pyimgmod.egg-info/top_level.txt