Metadata-Version: 2.1
Name: pyimgmod
Version: 0.0.1
Summary: Generating and modyfing inages
Author: Lemskyy (olek-program)
Author-email: <lemskyyyt+projects@gmail.com>
Keywords: python,image,py,png,library
Classifier: Development Status :: 1 - Planning
Classifier: Intended Audience :: Developers
Classifier: Programming Language :: Python :: 3
Classifier: Operating System :: Unix
Classifier: Operating System :: MacOS :: MacOS X
Classifier: Operating System :: Microsoft :: Windows
License-File: LICENSE
